morphometrics/__init__.py
morphometrics/_sample_data.py
morphometrics/_version.py
morphometrics/napari.yaml
morphometrics/types.py
morphometrics/_gui/__init__.py
morphometrics/_gui/_qt/__init__.py
morphometrics/_gui/_qt/annotation_widgets.py
morphometrics/_gui/_qt/labeling_widgets.py
morphometrics/_gui/_qt/measurement_widgets.py
morphometrics/_gui/_qt/multiple_viewer_widget.py
morphometrics/_gui/_qt/_tests/__init__.py
morphometrics/_gui/_qt/_tests/test_annotation_widgets.py
morphometrics/_gui/label_curator/__init__.py
morphometrics/_gui/label_curator/label_cleaning.py
morphometrics/_gui/label_curator/label_curator.py
morphometrics/_gui/label_curator/label_painting.py
morphometrics/_gui/label_curator/qt_label_curator.py
morphometrics/_gui/label_curator/_tests/__init__.py
morphometrics/_gui/label_curator/_tests/test_label_cleaning.py
morphometrics/_gui/label_curator/_tests/test_label_curator.py
morphometrics/_gui/models/__init__.py
morphometrics/_gui/models/annotation_model.py
morphometrics/_gui/models/labeling_model.py
morphometrics/_gui/models/_tests/__init__.py
morphometrics/_gui/models/_tests/test_annotation_model.py
morphometrics/_gui/models/_tests/test_labeling_model.py
morphometrics/_tests/__init__.py
morphometrics/_tests/test_sample_data.py
morphometrics/_tests/test_types.py
morphometrics/_tests/test_widget.py
morphometrics/classify/__init__.py
morphometrics/classify/classify_utils.py
morphometrics/classify/random_forest.py
morphometrics/data/__init__.py
morphometrics/data/intensity_image.py
morphometrics/data/label_image.py
morphometrics/explore/__init__.py
morphometrics/explore/cluster.py
morphometrics/explore/dimensionality_reduction.py
morphometrics/explore/explore_utils.py
morphometrics/explore/sample.py
morphometrics/explore/_tests/__init__.py
morphometrics/explore/_tests/_explore_test_utils.py
morphometrics/explore/_tests/test_cluster.py
morphometrics/explore/_tests/test_dimensionality_reduction.py
morphometrics/explore/_tests/test_explore_utils.py
morphometrics-0.0.8.dist-info/LICENSE
morphometrics-0.0.8.dist-info/METADATA
morphometrics-0.0.8.dist-info/WHEEL
morphometrics-0.0.8.dist-info/entry_points.txt
morphometrics-0.0.8.dist-info/top_level.txt
morphometrics-0.0.8.dist-info/RECORD
