Metadata-Version: 2.1
Name: morphometrics
Version: 0.0.8
Summary: A plugin for quantifying shape and neighborhoods from images.
Home-page: https://github.com/kevinyamauchi/morphometrics
Author: Kevin Yamauchi
Author-email: kevin.yamauchi@gmail.com
License: BSD-3-Clause
Project-URL: Bug Tracker, https://github.com/kevinyamauchi/morphometrics/issues
Project-URL: Documentation, https://github.com/kevinyamauchi/morphometrics#README.md
Project-URL: Source Code, https://github.com/kevinyamauchi/morphometrics
Project-URL: User Support, https://github.com/kevinyamauchi/morphometrics/issues
Classifier: Development Status :: 2 - Pre-Alpha
Classifier: Framework :: napari
Classifier: Intended Audience :: Developers
Classifier: License :: OSI Approved :: BSD License
Classifier: Operating System :: OS Independent
Classifier: Programming Language :: Python
Classifier: Programming Language :: Python :: 3
Classifier: Programming Language :: Python :: 3 :: Only
Classifier: Programming Language :: Python :: 3.9
Classifier: Topic :: Scientific/Engineering :: Image Processing
Requires-Python: >=3.9
License-File: LICENSE
Requires-Dist: glasbey
Requires-Dist: imageio (!=2.11.0,!=2.22.1,>=2.5.0)
Requires-Dist: leidenalg
Requires-Dist: napari-skimage-regionprops
Requires-Dist: napari
Requires-Dist: numba
Requires-Dist: numpy
Requires-Dist: qtpy
Requires-Dist: pandas
Requires-Dist: pooch
Requires-Dist: pyclesperanto-prototype (>=0.8.0)
Requires-Dist: pymeshfix
Requires-Dist: pyqtgraph
Requires-Dist: scanpy
Requires-Dist: scikit-image (>0.19.0)
Requires-Dist: scikit-learn (>=0.24.2)
Requires-Dist: tqdm
Requires-Dist: trimesh[easy]
Provides-Extra: dev
Requires-Dist: pre-commit ; extra == 'dev'
Requires-Dist: pytest ; extra == 'dev'
Requires-Dist: pytest-qt ; extra == 'dev'
